{
  "$schema": "https://mintlify.com/docs.json",
  "name": "Logo Generator Skill",
  "theme": "palm",
  "colors": {
    "primary": "#7C3AED",
    "light": "#EDE9FE",
    "dark": "#4C1D95"
  },
  "navbar": {
    "primary": {
      "type": "github",
      "href": "https://github.com/op7418/logo-generator-skill"
    }
  },
  "footer": {
    "socials": {
      "github": "https://github.com/op7418/logo-generator-skill"
    }
  },
  "navigation": {
    "tabs": [
      {
        "tab": "Documentation",
        "groups": [
          {
            "group": "Get Started",
            "pages": [
              "introduction",
              "installation",
              "quickstart"
            ]
          },
          {
            "group": "Using the Skill",
            "pages": [
              "guides/workflow",
              "guides/logo-generation",
              "guides/showcase-generation",
              "guides/iteration"
            ]
          },
          {
            "group": "Reference",
            "pages": [
              "reference/design-patterns",
              "reference/background-styles",
              "reference/scripts",
              "reference/configuration"
            ]
          }
        ]
      }
    ]
  }
}
